Metadata-Version: 2.1
Name: seeed-python-mlx90640
Version: 1.1.0
Summary: Python library for the Grove - Thermal Imaging Camera(MLX90640) is an thermal sensor. 
Home-page: https://github.com/Seeed-Studio/Seeed_Python_MLX90640
Author: Hanson
Author-email: 595355940@qq.com
License: MIT
Keywords: seeed grove mlx90640 thermal Camera sensor i2c hardware
Platform: UNKNOWN
Classifier: Development Status :: 3 - Alpha
Classifier: Intended Audience :: Developers
Classifier: Topic :: Software Development :: Libraries
Classifier: Topic :: System :: Hardware
Classifier: License :: OSI Approved :: MIT License
Classifier: Programming Language :: Python :: 3
Classifier: Programming Language :: Python :: 3.4
Classifier: Programming Language :: Python :: 3.5
Requires-Dist: grove.py
